trader/__init__.py
trader/display.py
trader/ma.py
trader/plotter.py
trader/processor.py
trader/queable.py
trader/rsi.py
trader/rsl.py
trader/stock.py
trader/trend.py
trader/utils.py
traderpy-1.0.7.dist-info/LICENSE
traderpy-1.0.7.dist-info/METADATA
traderpy-1.0.7.dist-info/WHEEL
traderpy-1.0.7.dist-info/top_level.txt
traderpy-1.0.7.dist-info/RECORD
