Metadata-Version: 2.1
Name: traderpy
Version: 1.0.7
License-File: LICENSE
Requires-Dist: yfinance
Requires-Dist: pandas
Requires-Dist: pygame
Requires-Dist: plotly
Requires-Dist: tqdm
Requires-Dist: scikit-learn
Requires-Dist: scipy
Requires-Dist: numpy
Requires-Dist: tabulate
